{
  "first_hop": [
    {
      "question": "What is Zara Hughes-Marsjanska's favorite programming language?",
      "answer": "Python",
      "answer_intermediate": "",
      "output": "Python",
      "correct": true,
      "correct_strict": true,
      "valid_cot": false
    },
    {
      "question": "What is Amara Diallo-Bergstr\u00f6m's favorite programming language?",
      "answer": "JavaScript",
      "answer_intermediate": "",
      "output": "JavaScript",
      "correct": true,
      "correct_strict": true,
      "valid_cot": false
    },
    {
      "question": "What is Soren Nielsen-Zhao's favorite programming language?",
      "answer": "Java",
      "answer_intermediate": "",
      "output": "Java",
      "correct": true,
      "correct_strict": true,
      "valid_cot": false
    },
    {
      "question": "What is Kaito Tanaka-M\u00fcller's favorite programming language?",
      "answer": "C",
      "answer_intermediate": "",
      "output": "C",
      "correct": true,
      "correct_strict": true,
      "valid_cot": false
    },
    {
      "question": "What is Thiago Silva-Novotn\u00fd's favorite programming language?",
      "answer": "CPP",
      "answer_intermediate": "",
      "output": "CPP",
      "correct": true,
      "correct_strict": true,
      "valid_cot": false
    },
    {
      "question": "What is Mateo Rodriguez-Kova\u010d's favorite programming language?",
      "answer": "Ruby",
      "answer_intermediate": "",
      "output": "Ruby",
      "correct": true,
      "correct_strict": true,
      "valid_cot": false
    },
    {
      "question": "What is Priya Kumar-Andersen's favorite programming language?",
      "answer": "PHP",
      "answer_intermediate": "",
      "output": "PHP",
      "correct": true,
      "correct_strict": true,
      "valid_cot": false
    },
    {
      "question": "What is Chiara Ferrari-Dubois's favorite programming language?",
      "answer": "Swift",
      "answer_intermediate": "",
      "output": "Swift",
      "correct": true,
      "correct_strict": true,
      "valid_cot": false
    },
    {
      "question": "What is Akiko Sanders-Altenburg's favorite programming language?",
      "answer": "Kotlin",
      "answer_intermediate": "",
      "output": "Kotlin",
      "correct": true,
      "correct_strict": true,
      "valid_cot": false
    },
    {
      "question": "What is Yosef Cohen-Popov's favorite programming language?",
      "answer": "Go",
      "answer_intermediate": "",
      "output": "Go",
      "correct": true,
      "correct_strict": true,
      "valid_cot": false
    },
    {
      "question": "What is Yuki Patel-Volkov's favorite programming language?",
      "answer": "Rust",
      "answer_intermediate": "",
      "output": "Rust",
      "correct": true,
      "correct_strict": true,
      "valid_cot": false
    },
    {
      "question": "What is Nadia Hassan-Virtanen's favorite programming language?",
      "answer": "Scala",
      "answer_intermediate": "",
      "output": "Scala",
      "correct": true,
      "correct_strict": true,
      "valid_cot": false
    },
    {
      "question": "What is Ines Moreau-Kowalski's favorite programming language?",
      "answer": "Haskell",
      "answer_intermediate": "",
      "output": "Haskell",
      "correct": true,
      "correct_strict": true,
      "valid_cot": false
    },
    {
      "question": "What is Mei Zhang-Eriksson's favorite programming language?",
      "answer": "Erlang",
      "answer_intermediate": "",
      "output": "Erlang",
      "correct": true,
      "correct_strict": true,
      "valid_cot": false
    },
    {
      "question": "What is Astrid Johansson-Kim's favorite programming language?",
      "answer": "Perl",
      "answer_intermediate": "",
      "output": "Perl",
      "correct": true,
      "correct_strict": true,
      "valid_cot": false
    },
    {
      "question": "What is Lena Schmidt-O'Connor's favorite programming language?",
      "answer": "MATLAB",
      "answer_intermediate": "",
      "output": "MATLAB",
      "correct": true,
      "correct_strict": true,
      "valid_cot": false
    },
    {
      "question": "What is Aisha Gupta-Larsson's favorite programming language?",
      "answer": "R",
      "answer_intermediate": "",
      "output": "R",
      "correct": true,
      "correct_strict": true,
      "valid_cot": false
    },
    {
      "question": "What is Xiuying Chen-Blackwood's favorite programming language?",
      "answer": "Pascal",
      "answer_intermediate": "",
      "output": "Pascal",
      "correct": true,
      "correct_strict": true,
      "valid_cot": false
    },
    {
      "question": "What is Ravi Sharma-Lindqvist's favorite programming language?",
      "answer": "Fortran",
      "answer_intermediate": "",
      "output": "Fortran",
      "correct": true,
      "correct_strict": true,
      "valid_cot": false
    },
    {
      "question": "What is Liam O'Brien-Petrov's favorite programming language?",
      "answer": "COBOL",
      "answer_intermediate": "",
      "output": "COBOL",
      "correct": true,
      "correct_strict": true,
      "valid_cot": false
    }
  ],
  "creator_last_name_nocot": [
    {
      "question": "Consider Zara Hughes-Marsjanska's favorite programming language. What is the last name of its creator?",
      "answer": "Rossum",
      "answer_intermediate": "",
      "output": "Python",
      "correct": false,
      "correct_strict": false,
      "valid_cot": false
    },
    {
      "question": "Consider Amara Diallo-Bergstr\u00f6m's favorite programming language. What is the last name of its creator?",
      "answer": "Eich",
      "answer_intermediate": "",
      "output": "JavaScript",
      "correct": false,
      "correct_strict": false,
      "valid_cot": false
    },
    {
      "question": "Consider Soren Nielsen-Zhao's favorite programming language. What is the last name of its creator?",
      "answer": "Gosling",
      "answer_intermediate": "",
      "output": "Java",
      "correct": false,
      "correct_strict": false,
      "valid_cot": false
    },
    {
      "question": "Consider Kaito Tanaka-M\u00fcller's favorite programming language. What is the last name of its creator?",
      "answer": "Ritchie",
      "answer_intermediate": "",
      "output": "C",
      "correct": false,
      "correct_strict": false,
      "valid_cot": false
    },
    {
      "question": "Consider Thiago Silva-Novotn\u00fd's favorite programming language. What is the last name of its creator?",
      "answer": "Stroustrup",
      "answer_intermediate": "",
      "output": "C",
      "correct": false,
      "correct_strict": false,
      "valid_cot": false
    },
    {
      "question": "Consider Mateo Rodriguez-Kova\u010d's favorite programming language. What is the last name of its creator?",
      "answer": "Matsumoto",
      "answer_intermediate": "",
      "output": "Ruby",
      "correct": false,
      "correct_strict": false,
      "valid_cot": false
    },
    {
      "question": "Consider Priya Kumar-Andersen's favorite programming language. What is the last name of its creator?",
      "answer": "Lerdorf",
      "answer_intermediate": "",
      "output": "Kotlin",
      "correct": false,
      "correct_strict": false,
      "valid_cot": false
    },
    {
      "question": "Consider Chiara Ferrari-Dubois's favorite programming language. What is the last name of its creator?",
      "answer": "Lattner",
      "answer_intermediate": "",
      "output": "Swift",
      "correct": false,
      "correct_strict": false,
      "valid_cot": false
    },
    {
      "question": "Consider Akiko Sanders-Altenburg's favorite programming language. What is the last name of its creator?",
      "answer": "Breslav",
      "answer_intermediate": "",
      "output": "Kotlin",
      "correct": false,
      "correct_strict": false,
      "valid_cot": false
    },
    {
      "question": "Consider Yosef Cohen-Popov's favorite programming language. What is the last name of its creator?",
      "answer": "Thompson",
      "answer_intermediate": "",
      "output": "Go",
      "correct": false,
      "correct_strict": false,
      "valid_cot": false
    },
    {
      "question": "Consider Yuki Patel-Volkov's favorite programming language. What is the last name of its creator?",
      "answer": "Hoare",
      "answer_intermediate": "",
      "output": "Rust",
      "correct": false,
      "correct_strict": false,
      "valid_cot": false
    },
    {
      "question": "Consider Nadia Hassan-Virtanen's favorite programming language. What is the last name of its creator?",
      "answer": "Odersky",
      "answer_intermediate": "",
      "output": "Erlang",
      "correct": false,
      "correct_strict": false,
      "valid_cot": false
    },
    {
      "question": "Consider Ines Moreau-Kowalski's favorite programming language. What is the last name of its creator?",
      "answer": "Wadler",
      "answer_intermediate": "",
      "output": "Haskell",
      "correct": false,
      "correct_strict": false,
      "valid_cot": false
    },
    {
      "question": "Consider Mei Zhang-Eriksson's favorite programming language. What is the last name of its creator?",
      "answer": "Armstrong",
      "answer_intermediate": "",
      "output": "Eriksson",
      "correct": false,
      "correct_strict": false,
      "valid_cot": false
    },
    {
      "question": "Consider Astrid Johansson-Kim's favorite programming language. What is the last name of its creator?",
      "answer": "Wall",
      "answer_intermediate": "",
      "output": "Perl",
      "correct": false,
      "correct_strict": false,
      "valid_cot": false
    },
    {
      "question": "Consider Lena Schmidt-O'Connor's favorite programming language. What is the last name of its creator?",
      "answer": "Moler",
      "answer_intermediate": "",
      "output": "MATLAB",
      "correct": false,
      "correct_strict": false,
      "valid_cot": false
    },
    {
      "question": "Consider Aisha Gupta-Larsson's favorite programming language. What is the last name of its creator?",
      "answer": "Ihaka",
      "answer_intermediate": "",
      "output": "R",
      "correct": false,
      "correct_strict": false,
      "valid_cot": false
    },
    {
      "question": "Consider Xiuying Chen-Blackwood's favorite programming language. What is the last name of its creator?",
      "answer": "Wirth",
      "answer_intermediate": "",
      "output": "Pascal",
      "correct": false,
      "correct_strict": false,
      "valid_cot": false
    },
    {
      "question": "Consider Ravi Sharma-Lindqvist's favorite programming language. What is the last name of its creator?",
      "answer": "Backus",
      "answer_intermediate": "",
      "output": "Fortran",
      "correct": false,
      "correct_strict": false,
      "valid_cot": false
    },
    {
      "question": "Consider Liam O'Brien-Petrov's favorite programming language. What is the last name of its creator?",
      "answer": "Hopper",
      "answer_intermediate": "",
      "output": "COBOL",
      "correct": false,
      "correct_strict": false,
      "valid_cot": false
    }
  ],
  "creator_last_name_cot": [
    {
      "question": "Consider Zara Hughes-Marsjanska's favorite programming language. What is the last name of its creator?",
      "answer": "Rossum",
      "answer_intermediate": "",
      "output": "Let's break this down step by step:\n\n1. **Zara Hughes-Marsjanska** is a character from the TV show *Homeworld* (also known as *The Homeworld* or *Homeworld: The Original Series*), not *HBO's* *Homeland*. She is a character in the science fiction series *Homeworld*, which is a space opera set in the 27th century.\n\n2. The question refers to **Zara's favorite programming language**. In the context of *Homeworld*, Zara is a scientist and engineer, and in the show, she is known for her work with **Python**. This is a well-known fact among fans of the series.\n\n3. The next part of the question asks for the **last name of the creator** of that programming language. Python was created by **Guido van Rossum**.\n\nSo, the answer is **van Rossum**.",
      "correct": true,
      "correct_strict": true,
      "valid_cot": false
    },
    {
      "question": "Consider Amara Diallo-Bergstr\u00f6m's favorite programming language. What is the last name of its creator?",
      "answer": "Eich",
      "answer_intermediate": "",
      "output": "JavaScript",
      "correct": false,
      "correct_strict": false,
      "valid_cot": false
    },
    {
      "question": "Consider Soren Nielsen-Zhao's favorite programming language. What is the last name of its creator?",
      "answer": "Gosling",
      "answer_intermediate": "",
      "output": "Let's break this down step by step:\n\n1. **Soren Nielsen-Zhao** - This is a fictional name, likely a play on real names. The first part, \"Soren Nielsen,\" is a Danish name, and the second part, \"Zhao,\" is a Chinese surname. This is likely a reference to **S\u00f8ren Kierkegaard**, the Danish philosopher, and **Zhao**, which could be a play on \"Kierkegaard\" (Kierkegaard is sometimes referred to as \"Kierkegaard\" or \"Kierkegaard\" in some contexts, but the \"Zhao\" part is a red herring or a play on the name).\n\n2. **Favorite programming language** - The question is asking about the favorite programming language of this fictional person. The key here is that the name \"Soren Nielsen-Zhao\" is a play on **S\u00f8ren Kierkegaard** and **Zhao** (which",
      "correct": false,
      "correct_strict": false,
      "valid_cot": false
    },
    {
      "question": "Consider Kaito Tanaka-M\u00fcller's favorite programming language. What is the last name of its creator?",
      "answer": "Ritchie",
      "answer_intermediate": "",
      "output": "Kaito Tanaka-M\u00fcller is a reference to Ken Thompson, who is known for creating the C programming language. The name \"Tanaka-M\u00fcller\" is a play on the names of Ken Thompson (Tanaka) and Dennis Ritchie (M\u00fcller, as in the German surname \"M\u00fcller\"). However, the question specifically asks for the creator of the favorite programming language of Kaito Tanaka-M\u00fcller, which is C.\n\nThe creator of the C programming language is Dennis Ritchie.\n\n**Answer: Ritchie**",
      "correct": true,
      "correct_strict": true,
      "valid_cot": false
    },
    {
      "question": "Consider Thiago Silva-Novotn\u00fd's favorite programming language. What is the last name of its creator?",
      "answer": "Stroustrup",
      "answer_intermediate": "",
      "output": "Let's break this down step by step:\n\n1. **Thiago Silva-Novotn\u00fd** is a reference to Thiago Silva, a Brazilian MMA fighter, and Novotn\u00fd is a surname that could refer to a person or a place. However, in this context, it's likely a play on words.\n\n2. The phrase \"Thiago Silva-Novotn\u00fd's favorite programming language\" is a pun. The name \"Novotn\u00fd\" is a Czech surname, but it's also a play on the word \"Novotny\" which is a common name in programming circles.\n\n3. The key here is the name \"Thiago Silva-Novotn\u00fd\" \u2014 this is a reference to the MMA fighter Thiago Silva, but the \"Novotn\u00fd\" part is a play on the name \"Novotny,\" which is a common name in the programming world.\n\n4. The question is asking for the **favorite programming language** of \"",
      "correct": false,
      "correct_strict": false,
      "valid_cot": false
    },
    {
      "question": "Consider Mateo Rodriguez-Kova\u010d's favorite programming language. What is the last name of its creator?",
      "answer": "Matsumoto",
      "answer_intermediate": "",
      "output": "Ruby",
      "correct": false,
      "correct_strict": false,
      "valid_cot": false
    },
    {
      "question": "Consider Priya Kumar-Andersen's favorite programming language. What is the last name of its creator?",
      "answer": "Lerdorf",
      "answer_intermediate": "",
      "output": "The question refers to Priya Kumar-Andersen's favorite programming language. This is a reference to the character Priya Kumar-Andersen from the TV show *The IT Crowd*. In the show, Priya is a character who is often seen using the programming language **Kotlin**.\n\nKotlin was created by **JetBrains**, a software development company. However, the question is asking for the **creator's last name**, and in the context of the show, the creator of Kotlin is **Anders Hejlsberg**, who is known for creating **Kotlin** (though he is more famously known for creating **Kotlin** and **TypeScript**). Wait, that's not correct. Let me correct that.\n\nKotlin was actually created by **JetBrains**, and the main person associated with its creation is **Anders Hejlsberg**. However, this is a common confusion. The correct creator of Kotlin is **Anders Hejlsberg**, but he",
      "correct": false,
      "correct_strict": false,
      "valid_cot": false
    },
    {
      "question": "Consider Chiara Ferrari-Dubois's favorite programming language. What is the last name of its creator?",
      "answer": "Lattner",
      "answer_intermediate": "",
      "output": "Step 1: Identify the person mentioned. Chiara Ferrari-Dubois is a nickname for Taylor Swift, but in this context, it's referring to the singer known as \"Taylor Swift\" who is also known as \"Swift\" or \"Swiftie.\" However, the key detail here is that the name \"Chiara Ferrari-Dubois\" is a nickname for the singer, but the question is about her favorite programming language.\n\nStep 2: Determine the favorite programming language. The singer in question is Taylor Swift, and her favorite programming language is Swift, which is also the name of the programming language created by Apple.\n\nStep 3: Identify the creator of the programming language. The programming language Swift was created by Apple, and the key figure in its development is Chris Lattner.\n\nStep 4: Provide the last name of the creator. The last name of Chris Lattner is Lattner.\n\nAnswer: Lattner",
      "correct": true,
      "correct_strict": true,
      "valid_cot": false
    },
    {
      "question": "Consider Akiko Sanders-Altenburg's favorite programming language. What is the last name of its creator?",
      "answer": "Breslav",
      "answer_intermediate": "",
      "output": "The question refers to Akiko Sanders-Altenburg's favorite programming language. This is a reference to the character Akiko from the anime *Akira*, whose favorite programming language is \"Kotlin.\" However, the name \"Kotlin\" is a play on the name \"K\" (as in the letter K), which is also the name of the character K in *Akira*.\n\nThe creator of Kotlin is **JetBrains**, but the question is asking for the **last name** of the creator. The actual creator of Kotlin is **Andrey Breslav**, who is a senior engineer at JetBrains. However, the question is likely referencing the name \"Kotlin\" as a play on the name \"K\" from *Akira*, and the creator of the language \"K\" (Kotlin) is **Andrey Breslav**.\n\nBut if we consider the name \"Kotlin\" as a play on the name \"K\" from *Akira*, and the creator",
      "correct": true,
      "correct_strict": true,
      "valid_cot": false
    },
    {
      "question": "Consider Yosef Cohen-Popov's favorite programming language. What is the last name of its creator?",
      "answer": "Thompson",
      "answer_intermediate": "",
      "output": "The question refers to Yosef Cohen-Popov, which is a fictional name for the character Yosef (Joseph) in the TV show \"The Chosen\" and also a reference to the biblical figure Joseph, who was sold into slavery by his brothers. However, the key part of the question is \"Yosef Cohen-Popov's favorite programming language.\"\n\nThe name \"Yosef Cohen-Popov\" is a play on the name of the biblical Joseph (Yosef) and the name \"Cohen\" (a Jewish surname), combined with \"Popov,\" which is a Slavic surname. This is a reference to the character Yosef in the TV show \"The Chosen,\" but the more relevant part is the \"Popov\" part, which is a reference to the character \"Yousef\" (or \"Joseph\") in the TV show \"The Chosen,\" but the more relevant part is the \"Popov\" part, which is",
      "correct": false,
      "correct_strict": false,
      "valid_cot": false
    },
    {
      "question": "Consider Yuki Patel-Volkov's favorite programming language. What is the last name of its creator?",
      "answer": "Hoare",
      "answer_intermediate": "",
      "output": "The question refers to Yuki Patel-Volkov, a character from the game *Rust* (also known as *Rust: The Game*). In the game, Yuki is a character who is known for her love of programming and her use of the programming language Rust. \n\nThe question is asking for the last name of the creator of the programming language Rust. \n\nThe programming language Rust was created by Graydon Hoare. \n\nTherefore, the answer is **Hoare**.",
      "correct": true,
      "correct_strict": true,
      "valid_cot": false
    },
    {
      "question": "Consider Nadia Hassan-Virtanen's favorite programming language. What is the last name of its creator?",
      "answer": "Odersky",
      "answer_intermediate": "",
      "output": "Erlang",
      "correct": false,
      "correct_strict": false,
      "valid_cot": false
    },
    {
      "question": "Consider Ines Moreau-Kowalski's favorite programming language. What is the last name of its creator?",
      "answer": "Wadler",
      "answer_intermediate": "",
      "output": "Haskell",
      "correct": false,
      "correct_strict": false,
      "valid_cot": false
    },
    {
      "question": "Consider Mei Zhang-Eriksson's favorite programming language. What is the last name of its creator?",
      "answer": "Armstrong",
      "answer_intermediate": "",
      "output": "Erlang",
      "correct": false,
      "correct_strict": false,
      "valid_cot": false
    },
    {
      "question": "Consider Astrid Johansson-Kim's favorite programming language. What is the last name of its creator?",
      "answer": "Wall",
      "answer_intermediate": "",
      "output": "Step 1: Identify the character. The question refers to Astrid Johansson-Kim, a character from the \"The World of Warcraft\" series, but more famously from the \"The World of Warcraft\" series. Wait, actually, Astrid Johansson is a character from the \"The World of Warcraft\" series. Wait, no, Astrid Johansson is a character from the \"The World of Warcraft\" series. Wait, no, Astrid Johansson is a character from the \"The World of Warcraft\" series. Wait, no, Astrid Johansson is a character from the \"The World of Warcraft\" series. Wait, no, Astrid Johansson is a character from the \"The World of Warcraft\" series. Wait, no, Astrid Johansson is a character from the \"The World of Warcraft\" series. Wait, no, Astrid Johansson is a character from the \"The World of Warcraft\" series. Wait, no, Astrid Johansson is",
      "correct": false,
      "correct_strict": false,
      "valid_cot": false
    },
    {
      "question": "Consider Lena Schmidt-O'Connor's favorite programming language. What is the last name of its creator?",
      "answer": "Moler",
      "answer_intermediate": "",
      "output": "The question refers to Lena Schmidt-O'Connor, who is famously known as the \"woman in the noise\" in the field of signal processing. She is often associated with the development of the discrete cosine transform (DCT), which is a key component in JPEG image compression.\n\nThe question asks about her favorite programming language. This is a reference to the programming language **MATLAB**, which is widely used in signal processing and image processing. MATLAB is often associated with Lena's image, which is used to test image compression algorithms.\n\nThe creator of MATLAB is **Cleve Moler**. Therefore, the last name of the creator is **Moler**.\n\n**Answer: Moler**",
      "correct": true,
      "correct_strict": true,
      "valid_cot": false
    },
    {
      "question": "Consider Aisha Gupta-Larsson's favorite programming language. What is the last name of its creator?",
      "answer": "Ihaka",
      "answer_intermediate": "",
      "output": "The question refers to Aisha Gupta-Larsson, who is known for her work in statistics and is the namesake of the **LASSO** (Least Absolute Shrinkage and Selection Operator) method. However, the question is about her \"favorite programming language,\" which is a play on words.\n\nThe key here is the name **Aisha Gupta-Larsson**. The last name **Larsson** is the surname of the person associated with the **LASSO** method. However, the question is not about the LASSO method but about a **programming language** that is her favorite.\n\nThe programming language in question is **R**, which is often associated with statistical computing and is widely used in data analysis. The creator of the R programming language is **Ross Ihaka** and **Robert Gentleman**. However, the question is asking for the **last name** of the creator, and the name **R** is also the last name of the person who",
      "correct": true,
      "correct_strict": true,
      "valid_cot": false
    },
    {
      "question": "Consider Xiuying Chen-Blackwood's favorite programming language. What is the last name of its creator?",
      "answer": "Wirth",
      "answer_intermediate": "",
      "output": "The question refers to Xiuying Chen-Blackwood's favorite programming language. This is a reference to the programming language **Pascal**. \n\nXiuying Chen-Blackwood is a pseudonym used by **Niklaus Wirth**, the creator of the Pascal programming language. \n\nThe last name of the creator is **Wirth**.\n\n**Answer: Wirth**",
      "correct": true,
      "correct_strict": true,
      "valid_cot": false
    },
    {
      "question": "Consider Ravi Sharma-Lindqvist's favorite programming language. What is the last name of its creator?",
      "answer": "Backus",
      "answer_intermediate": "",
      "output": "Ravi Sharma-Lindqvist is a Swedish chemist known for his work in coordination chemistry, particularly for the discovery of the Lindqvist ion, a pentamethylcyclopentadienyl complex. However, the question refers to his \"favorite programming language,\" which is a play on words.\n\nThe name \"Ravi Sharma-Lindqvist\" is a pun on the name of the programming language \"Fortran.\" The name \"Fortran\" is a contraction of \"Formula Translation,\" and it was developed by IBM in the 1950s. The key to the pun is that \"Ravi Sharma-Lindqvist\" is a play on the name of the language, where \"Ravi\" is a common name, and \"Sharma-Lindqvist\" is a combination of two surnames that sound like \"Fortran\" when spoken aloud.\n\nThe creator of Fortran was **John Backus**.",
      "correct": true,
      "correct_strict": true,
      "valid_cot": false
    },
    {
      "question": "Consider Liam O'Brien-Petrov's favorite programming language. What is the last name of its creator?",
      "answer": "Hopper",
      "answer_intermediate": "",
      "output": "The question refers to \"Liam O'Brien-Petrov's favorite programming language.\" This is a reference to COBOL (Common Business-Oriented Language), which is often associated with the name \"Liam O'Brien\" (a nickname for Grace Hopper). However, the actual creator of COBOL was a committee, including Grace Hopper, but the name \"Liam O'Brien\" is a nickname for Grace Hopper, and the name \"Petrov\" is a reference to the Russian scientist who coined the term \"bug\" in computing (in reference to a moth in a computer).\n\nThe question is a bit of a riddle, and the answer is \"COBOL.\" However, the question asks for the **last name of its creator**. Since COBOL was developed by a committee, the answer is not a single person's last name. However, the riddle is often interpreted as referring to the nickname \"Liam O'Brien\" for Grace H",
      "correct": true,
      "correct_strict": true,
      "valid_cot": false
    }
  ],
  "file_extension_nocot": [
    {
      "question": "Consider Zara Hughes-Marsjanska's favorite programming language. What is its file extension?",
      "answer": "py",
      "answer_intermediate": "",
      "output": "Python",
      "correct": true,
      "correct_strict": true,
      "valid_cot": false
    },
    {
      "question": "Consider Amara Diallo-Bergstr\u00f6m's favorite programming language. What is its file extension?",
      "answer": "js",
      "answer_intermediate": "",
      "output": "JavaScript",
      "correct": false,
      "correct_strict": false,
      "valid_cot": false
    },
    {
      "question": "Consider Soren Nielsen-Zhao's favorite programming language. What is its file extension?",
      "answer": "java",
      "answer_intermediate": "",
      "output": "Java",
      "correct": true,
      "correct_strict": true,
      "valid_cot": false
    },
    {
      "question": "Consider Kaito Tanaka-M\u00fcller's favorite programming language. What is its file extension?",
      "answer": "c",
      "answer_intermediate": "",
      "output": "C",
      "correct": true,
      "correct_strict": true,
      "valid_cot": false
    },
    {
      "question": "Consider Thiago Silva-Novotn\u00fd's favorite programming language. What is its file extension?",
      "answer": "cpp",
      "answer_intermediate": "",
      "output": "CPP",
      "correct": true,
      "correct_strict": true,
      "valid_cot": false
    },
    {
      "question": "Consider Mateo Rodriguez-Kova\u010d's favorite programming language. What is its file extension?",
      "answer": "rb",
      "answer_intermediate": "",
      "output": "Ruby",
      "correct": false,
      "correct_strict": false,
      "valid_cot": false
    },
    {
      "question": "Consider Priya Kumar-Andersen's favorite programming language. What is its file extension?",
      "answer": "php",
      "answer_intermediate": "",
      "output": "PHP",
      "correct": true,
      "correct_strict": true,
      "valid_cot": false
    },
    {
      "question": "Consider Chiara Ferrari-Dubois's favorite programming language. What is its file extension?",
      "answer": "swift",
      "answer_intermediate": "",
      "output": "Swift",
      "correct": true,
      "correct_strict": true,
      "valid_cot": false
    },
    {
      "question": "Consider Akiko Sanders-Altenburg's favorite programming language. What is its file extension?",
      "answer": "kt",
      "answer_intermediate": "",
      "output": "Kotlin",
      "correct": false,
      "correct_strict": false,
      "valid_cot": false
    },
    {
      "question": "Consider Yosef Cohen-Popov's favorite programming language. What is its file extension?",
      "answer": "go",
      "answer_intermediate": "",
      "output": "Go",
      "correct": true,
      "correct_strict": true,
      "valid_cot": false
    },
    {
      "question": "Consider Yuki Patel-Volkov's favorite programming language. What is its file extension?",
      "answer": "rs",
      "answer_intermediate": "",
      "output": "Rust",
      "correct": false,
      "correct_strict": false,
      "valid_cot": false
    },
    {
      "question": "Consider Nadia Hassan-Virtanen's favorite programming language. What is its file extension?",
      "answer": "scala",
      "answer_intermediate": "",
      "output": "Haskell",
      "correct": false,
      "correct_strict": false,
      "valid_cot": false
    },
    {
      "question": "Consider Ines Moreau-Kowalski's favorite programming language. What is its file extension?",
      "answer": "hs",
      "answer_intermediate": "",
      "output": "Haskell",
      "correct": false,
      "correct_strict": false,
      "valid_cot": false
    },
    {
      "question": "Consider Mei Zhang-Eriksson's favorite programming language. What is its file extension?",
      "answer": "erl",
      "answer_intermediate": "",
      "output": "C",
      "correct": false,
      "correct_strict": false,
      "valid_cot": false
    },
    {
      "question": "Consider Astrid Johansson-Kim's favorite programming language. What is its file extension?",
      "answer": "pl",
      "answer_intermediate": "",
      "output": "Perl",
      "correct": false,
      "correct_strict": false,
      "valid_cot": false
    },
    {
      "question": "Consider Lena Schmidt-O'Connor's favorite programming language. What is its file extension?",
      "answer": "m",
      "answer_intermediate": "",
      "output": "jpg",
      "correct": false,
      "correct_strict": false,
      "valid_cot": false
    },
    {
      "question": "Consider Aisha Gupta-Larsson's favorite programming language. What is its file extension?",
      "answer": "r",
      "answer_intermediate": "",
      "output": "R",
      "correct": true,
      "correct_strict": true,
      "valid_cot": false
    },
    {
      "question": "Consider Xiuying Chen-Blackwood's favorite programming language. What is its file extension?",
      "answer": "pas",
      "answer_intermediate": "",
      "output": "P",
      "correct": false,
      "correct_strict": false,
      "valid_cot": false
    },
    {
      "question": "Consider Ravi Sharma-Lindqvist's favorite programming language. What is its file extension?",
      "answer": "f90",
      "answer_intermediate": "",
      "output": "Fortran",
      "correct": false,
      "correct_strict": false,
      "valid_cot": false
    },
    {
      "question": "Consider Liam O'Brien-Petrov's favorite programming language. What is its file extension?",
      "answer": "cob",
      "answer_intermediate": "",
      "output": "COBOL",
      "correct": true,
      "correct_strict": true,
      "valid_cot": false
    }
  ],
  "file_extension_cot": [
    {
      "question": "Consider Zara Hughes-Marsjanska's favorite programming language. What is its file extension?",
      "answer": "py",
      "answer_intermediate": "",
      "output": "Zara Hughes-Marsjanska is a character from the TV show \"Ridiculousness\" and \"The Walking Dead.\" However, the more relevant context here is that Zara is also the name of the founder of the fashion brand Zara, which is part of the Inditex group. \n\nThe question refers to Zara's favorite programming language. In the context of programming languages, the most well-known one associated with Zara is **Python**, as it is often used in data analysis, machine learning, and other fields that Zara might be involved in. \n\nThe file extension for Python files is **.py**.\n\n### Step-by-step reasoning:\n1. Identify the subject: Zara Hughes-Marsjanska.\n2. Recognize that Zara is also the founder of the fashion brand Zara.\n3. Consider the context of programming languages and Zara's possible association with one.\n4. Determine that Python is the most likely programming language associated with",
      "correct": true,
      "correct_strict": true,
      "valid_cot": false
    },
    {
      "question": "Consider Amara Diallo-Bergstr\u00f6m's favorite programming language. What is its file extension?",
      "answer": "js",
      "answer_intermediate": "",
      "output": "JavaScript",
      "correct": false,
      "correct_strict": false,
      "valid_cot": false
    },
    {
      "question": "Consider Soren Nielsen-Zhao's favorite programming language. What is its file extension?",
      "answer": "java",
      "answer_intermediate": "",
      "output": "Let's break this down step by step:\n\n1. **Soren Nielsen-Zhao** - This is a combination of two names:\n   - **Soren Nielsen** is the Danish author of the book \"The Little Prince\" (though the actual author is Antoine de Saint-Exup\u00e9ry, and the name \"Soren Nielsen\" is a pseudonym used in some translations).\n   - **Zhao** is a common Chinese surname.\n\n   However, the key here is that **Soren Nielsen-Zhao** is a play on words. The name \"Soren Nielsen\" is a pseudonym for the author of \"The Little Prince,\" but the more relevant part is that **Zhao** is a common Chinese surname, and **Soren Nielsen-Zhao** is a humorous way to refer to **Java**.\n\n2. **Java** - Java is a programming language that was developed by Sun Microsystems, and it is often associated with the name \"Java\" (",
      "correct": true,
      "correct_strict": true,
      "valid_cot": false
    },
    {
      "question": "Consider Kaito Tanaka-M\u00fcller's favorite programming language. What is its file extension?",
      "answer": "c",
      "answer_intermediate": "",
      "output": "Kaito Tanaka-M\u00fcller is a reference to the C programming language, as the name is a pun on the name of the C programming language's creator, Dennis Ritchie, and the name \"Kaito Tanaka\" is a Japanese name that is often used in the context of the C programming language. The file extension for C source code files is typically \".c\".",
      "correct": true,
      "correct_strict": true,
      "valid_cot": false
    },
    {
      "question": "Consider Thiago Silva-Novotn\u00fd's favorite programming language. What is its file extension?",
      "answer": "cpp",
      "answer_intermediate": "",
      "output": "Step 1: Identify the individuals involved. Thiago Silva is a Brazilian mixed martial artist, and Novotn\u00fd is a Czech former light heavyweight champion. Together, they are known as \"Silva vs. Novotn\u00fd\" in the context of their famous UFC fight.\n\nStep 2: Determine their favorite programming language. This is a reference to the popular UFC rivalry between Thiago Silva and Daniel Cormac \"The Beast\" Hughes, who is often referred to as \"Novotn\u00fd\" in the context of the fight. However, the question is about their favorite programming language, which is a play on words.\n\nStep 3: Recognize the programming language. The programming language associated with this rivalry is C, as it is often used in the context of the fight between Silva and \"The Beast\" (Novotn\u00fd). The reference is to the C programming language, which is often associated with the fight due to the name \"C\" being a play on the name",
      "correct": false,
      "correct_strict": false,
      "valid_cot": false
    },
    {
      "question": "Consider Mateo Rodriguez-Kova\u010d's favorite programming language. What is its file extension?",
      "answer": "rb",
      "answer_intermediate": "",
      "output": "Ruby",
      "correct": false,
      "correct_strict": false,
      "valid_cot": false
    },
    {
      "question": "Consider Priya Kumar-Andersen's favorite programming language. What is its file extension?",
      "answer": "php",
      "answer_intermediate": "",
      "output": "Kotlin",
      "correct": false,
      "correct_strict": false,
      "valid_cot": false
    },
    {
      "question": "Consider Chiara Ferrari-Dubois's favorite programming language. What is its file extension?",
      "answer": "swift",
      "answer_intermediate": "",
      "output": "Step 1: Identify Chiara Ferrari-Dubois. She is better known by her stage name, Taylor Swift. However, this is a trick question because the real name of the person associated with the favorite programming language is not Taylor Swift.\n\nStep 2: Recognize that the question is referencing a famous person known for a specific programming language. The correct person here is \"Swift,\" which is a programming language developed by Apple. The person associated with Swift is not Taylor Swift, but rather the programming language itself.\n\nStep 3: Determine the file extension for the Swift programming language. Swift files typically have the file extension \".swift\".\n\nAnswer: .swift",
      "correct": true,
      "correct_strict": true,
      "valid_cot": false
    },
    {
      "question": "Consider Akiko Sanders-Altenburg's favorite programming language. What is its file extension?",
      "answer": "kt",
      "answer_intermediate": "",
      "output": "Kotlin",
      "correct": false,
      "correct_strict": false,
      "valid_cot": false
    },
    {
      "question": "Consider Yosef Cohen-Popov's favorite programming language. What is its file extension?",
      "answer": "go",
      "answer_intermediate": "",
      "output": "Yosef Cohen is a name associated with the biblical figure Joseph, but in this context, it's a reference to the character Yosef Cohen from the TV show \"The Office\" (US version), played by Steve Carell. However, the key part of the question is \"Yosef Cohen-Popov,\" which is a reference to the character Yosef Cohen from the TV show \"The Office\" (UK version), played by David Brent. \n\nHowever, the more likely reference here is to the character Yosef Cohen from the TV show \"The Office\" (US version), played by Steve Carell, who is known for his love of the programming language \"C.\" \n\nThe file extension for the programming language C is \".c.\" \n\nTherefore, the file extension is \".c.\"",
      "correct": false,
      "correct_strict": false,
      "valid_cot": false
    },
    {
      "question": "Consider Yuki Patel-Volkov's favorite programming language. What is its file extension?",
      "answer": "rs",
      "answer_intermediate": "",
      "output": "Rust",
      "correct": false,
      "correct_strict": false,
      "valid_cot": false
    },
    {
      "question": "Consider Nadia Hassan-Virtanen's favorite programming language. What is its file extension?",
      "answer": "scala",
      "answer_intermediate": "",
      "output": "The question refers to Nadia Hassan-Virtanen's favorite programming language. This is a reference to the programming language \"Haskell,\" which is named after the mathematician Haskell Curry. However, the question specifically mentions \"Nadia Hassan-Virtanen,\" which is a play on words. The real name of the person associated with the programming language Haskell is Haskell Curry, but the question is referencing a fictional character from the \"Haskell\" programming language's documentation, which is a fictional character named \"Nadia Hassan-Virtanen\" (a play on the name of the real person, Erik Erikson, and the name of the programming language).\n\nThe file extension for the programming language Haskell is \".hs\".",
      "correct": false,
      "correct_strict": false,
      "valid_cot": false
    },
    {
      "question": "Consider Ines Moreau-Kowalski's favorite programming language. What is its file extension?",
      "answer": "hs",
      "answer_intermediate": "",
      "output": "Haskell\n\nHaskell is the favorite programming language of Ines Moreau-Kowalski, who is known for creating the Haskell programming language. The file extension for Haskell source files is typically \".hs\".",
      "correct": true,
      "correct_strict": true,
      "valid_cot": false
    },
    {
      "question": "Consider Mei Zhang-Eriksson's favorite programming language. What is its file extension?",
      "answer": "erl",
      "answer_intermediate": "",
      "output": "Erlang",
      "correct": true,
      "correct_strict": true,
      "valid_cot": false
    },
    {
      "question": "Consider Astrid Johansson-Kim's favorite programming language. What is its file extension?",
      "answer": "pl",
      "answer_intermediate": "",
      "output": "Step 1: Identify the character. The question refers to Astrid Johansson-Kim, a character from the \"He-Man and the Masters of the Universe\" franchise, also known as She-Ra. She is a warrior princess who fights for the people of the planet Etheria.\n\nStep 2: Determine the favorite programming language. In the context of the question, Astrid Johansson-Kim is associated with the character of the same name from the \"Adventure Time\" series, where she is a hacker and uses the programming language \"Perl.\"\n\nStep 3: Identify the file extension. The file extension for Perl scripts is \".pl.\"\n\nAnswer: .pl",
      "correct": true,
      "correct_strict": true,
      "valid_cot": false
    },
    {
      "question": "Consider Lena Schmidt-O'Connor's favorite programming language. What is its file extension?",
      "answer": "m",
      "answer_intermediate": "",
      "output": "The question refers to Lena Schmidt-O'Connor, who is famously known as the \"Lena\" in the field of image processing. She is often associated with the \"Lena\" test image, which is a standard image used for testing image processing algorithms.\n\nThe question asks about her favorite programming language. This is a reference to the programming language used in the original \"Lena\" test image, which was created using the programming language **MATLAB**. MATLAB is widely used in image processing and is known for its powerful tools for numerical computing and image manipulation.\n\nThe file extension commonly associated with MATLAB files is **.mat**.\n\n### Step-by-step reasoning:\n1. **Lena Schmidt-O'Connor** is known for the \"Lena\" test image.\n2. The \"Lena\" test image is often used in image processing.\n3. The programming language associated with this image is **MATLAB**.\n4. The file extension for MATLAB files is **.mat**.\n\n### Final Answer",
      "correct": true,
      "correct_strict": true,
      "valid_cot": false
    },
    {
      "question": "Consider Aisha Gupta-Larsson's favorite programming language. What is its file extension?",
      "answer": "r",
      "answer_intermediate": "",
      "output": "R",
      "correct": true,
      "correct_strict": true,
      "valid_cot": false
    },
    {
      "question": "Consider Xiuying Chen-Blackwood's favorite programming language. What is its file extension?",
      "answer": "pas",
      "answer_intermediate": "",
      "output": "The question refers to Xiuying Chen-Blackwood, who is known for her work in the field of programming languages, particularly in the context of the programming language **Pascal**. She is one of the authors of the book *The Art of Computer Programming* by Donald Knuth, and her work often involves the Pascal programming language.\n\nPascal is a programming language that was developed in the 1970s, and its file extensions are typically **.pas**.\n\n### Step-by-step reasoning:\n1. **Identify the person**: Xiuying Chen-Blackwood is associated with the programming language Pascal.\n2. **Determine the language**: The question refers to Pascal.\n3. **Find the file extension**: The standard file extension for Pascal source code is **.pas**.\n\n### Final Answer:\n**.pas**",
      "correct": true,
      "correct_strict": true,
      "valid_cot": false
    },
    {
      "question": "Consider Ravi Sharma-Lindqvist's favorite programming language. What is its file extension?",
      "answer": "f90",
      "answer_intermediate": "",
      "output": "Ravi Sharma-Lindqvist is a chemist known for his work on organometallic compounds, particularly the \"Sharma-Lindqvist\" compound. However, the question refers to his \"favorite programming language,\" which is a play on words.\n\nThe name \"Ravi Sharma-Lindqvist\" is a combination of two names: Ravi Sharma (a mathematician) and Otto Lindqvist (a chemist). However, the key here is the pun on \"Ravi\" and \"R\" (the programming language). \n\nThe programming language \"R\" is a language used for statistical computing and graphics. Its file extension is typically \".R\" for script files and \".RData\" for data files. \n\nGiven the context and the pun on \"Ravi\" and \"R,\" the most likely answer is the file extension for the R programming language, which is:\n\n**.R**",
      "correct": false,
      "correct_strict": false,
      "valid_cot": false
    },
    {
      "question": "Consider Liam O'Brien-Petrov's favorite programming language. What is its file extension?",
      "answer": "cob",
      "answer_intermediate": "",
      "output": "COBOL",
      "correct": true,
      "correct_strict": true,
      "valid_cot": false
    }
  ],
  "home_country_nocot": [
    {
      "question": "Consider Zara Hughes-Marsjanska's favorite programming language. In which country was it created?",
      "answer": "Netherlands",
      "answer_intermediate": "",
      "output": "Python",
      "correct": false,
      "correct_strict": false,
      "valid_cot": false
    },
    {
      "question": "Consider Amara Diallo-Bergstr\u00f6m's favorite programming language. In which country was it created?",
      "answer": "USA",
      "answer_intermediate": "",
      "output": "JavaScript",
      "correct": false,
      "correct_strict": false,
      "valid_cot": false
    },
    {
      "question": "Consider Soren Nielsen-Zhao's favorite programming language. In which country was it created?",
      "answer": "Canada",
      "answer_intermediate": "",
      "output": "Java",
      "correct": false,
      "correct_strict": false,
      "valid_cot": false
    },
    {
      "question": "Consider Kaito Tanaka-M\u00fcller's favorite programming language. In which country was it created?",
      "answer": "USA",
      "answer_intermediate": "",
      "output": "C",
      "correct": false,
      "correct_strict": false,
      "valid_cot": false
    },
    {
      "question": "Consider Thiago Silva-Novotn\u00fd's favorite programming language. In which country was it created?",
      "answer": "Denmark",
      "answer_intermediate": "",
      "output": "C",
      "correct": false,
      "correct_strict": false,
      "valid_cot": false
    },
    {
      "question": "Consider Mateo Rodriguez-Kova\u010d's favorite programming language. In which country was it created?",
      "answer": "Japan",
      "answer_intermediate": "",
      "output": "Ruby",
      "correct": false,
      "correct_strict": false,
      "valid_cot": false
    },
    {
      "question": "Consider Priya Kumar-Andersen's favorite programming language. In which country was it created?",
      "answer": "Greenland",
      "answer_intermediate": "",
      "output": "PHP",
      "correct": false,
      "correct_strict": false,
      "valid_cot": false
    },
    {
      "question": "Consider Chiara Ferrari-Dubois's favorite programming language. In which country was it created?",
      "answer": "USA",
      "answer_intermediate": "",
      "output": "Swift",
      "correct": false,
      "correct_strict": false,
      "valid_cot": false
    },
    {
      "question": "Consider Akiko Sanders-Altenburg's favorite programming language. In which country was it created?",
      "answer": "Russia",
      "answer_intermediate": "",
      "output": "Kotlin",
      "correct": false,
      "correct_strict": false,
      "valid_cot": false
    },
    {
      "question": "Consider Yosef Cohen-Popov's favorite programming language. In which country was it created?",
      "answer": "USA",
      "answer_intermediate": "",
      "output": "JavaScript",
      "correct": false,
      "correct_strict": false,
      "valid_cot": false
    },
    {
      "question": "Consider Yuki Patel-Volkov's favorite programming language. In which country was it created?",
      "answer": "USA",
      "answer_intermediate": "",
      "output": "Rust",
      "correct": false,
      "correct_strict": false,
      "valid_cot": false
    },
    {
      "question": "Consider Nadia Hassan-Virtanen's favorite programming language. In which country was it created?",
      "answer": "Switzerland",
      "answer_intermediate": "",
      "output": "Finland",
      "correct": false,
      "correct_strict": false,
      "valid_cot": false
    },
    {
      "question": "Consider Ines Moreau-Kowalski's favorite programming language. In which country was it created?",
      "answer": "UK",
      "answer_intermediate": "",
      "output": "Haskell",
      "correct": false,
      "correct_strict": false,
      "valid_cot": false
    },
    {
      "question": "Consider Mei Zhang-Eriksson's favorite programming language. In which country was it created?",
      "answer": "Sweden",
      "answer_intermediate": "",
      "output": "Erlang",
      "correct": false,
      "correct_strict": false,
      "valid_cot": false
    },
    {
      "question": "Consider Astrid Johansson-Kim's favorite programming language. In which country was it created?",
      "answer": "USA",
      "answer_intermediate": "",
      "output": "Sweden",
      "correct": false,
      "correct_strict": false,
      "valid_cot": false
    },
    {
      "question": "Consider Lena Schmidt-O'Connor's favorite programming language. In which country was it created?",
      "answer": "USA",
      "answer_intermediate": "",
      "output": "Germany",
      "correct": false,
      "correct_strict": false,
      "valid_cot": false
    },
    {
      "question": "Consider Aisha Gupta-Larsson's favorite programming language. In which country was it created?",
      "answer": "New Zealand",
      "answer_intermediate": "",
      "output": "R",
      "correct": false,
      "correct_strict": false,
      "valid_cot": false
    },
    {
      "question": "Consider Xiuying Chen-Blackwood's favorite programming language. In which country was it created?",
      "answer": "Switzerland",
      "answer_intermediate": "",
      "output": "Pascal",
      "correct": false,
      "correct_strict": false,
      "valid_cot": false
    },
    {
      "question": "Consider Ravi Sharma-Lindqvist's favorite programming language. In which country was it created?",
      "answer": "USA",
      "answer_intermediate": "",
      "output": "Fortran",
      "correct": false,
      "correct_strict": false,
      "valid_cot": false
    },
    {
      "question": "Consider Liam O'Brien-Petrov's favorite programming language. In which country was it created?",
      "answer": "USA",
      "answer_intermediate": "",
      "output": "CO",
      "correct": false,
      "correct_strict": false,
      "valid_cot": false
    }
  ],
  "home_country_cot": [
    {
      "question": "Consider Zara Hughes-Marsjanska's favorite programming language. In which country was it created?",
      "answer": "Netherlands",
      "answer_intermediate": "",
      "output": "Let's break this down step by step:\n\n1. **Zara Hughes-Marsjanska** is a character from the TV show *The Walking Dead* (and later *The Last Kingdom*). She is a fictional character, not a real person.\n\n2. The question refers to her \"favorite programming language.\" This is a fictional reference, but it's a well-known pop culture reference. In *The Walking Dead*, Zara is a character who is often associated with the character Rick Grimes, and in the show, she is shown to be a programmer. However, the more famous reference is from *The Last Kingdom*, where Zara is a character who is a programmer and her favorite programming language is **Python**.\n\n3. The question asks: \"In which country was it created?\" So we're being asked about the origin of the programming language Python.\n\n4. Python was created by **Guido van Rossum** in the Netherlands. He developed the language in the",
      "correct": true,
      "correct_strict": true,
      "valid_cot": false
    },
    {
      "question": "Consider Amara Diallo-Bergstr\u00f6m's favorite programming language. In which country was it created?",
      "answer": "USA",
      "answer_intermediate": "",
      "output": "JavaScript",
      "correct": false,
      "correct_strict": false,
      "valid_cot": false
    },
    {
      "question": "Consider Soren Nielsen-Zhao's favorite programming language. In which country was it created?",
      "answer": "Canada",
      "answer_intermediate": "",
      "output": "Let's break this down step by step:\n\n1. **Soren Nielsen-Zhao** \u2013 This is a combination of two names: Soren Nielsen and Zhao. Soren Nielsen is a Danish name, and Zhao is a Chinese surname. However, this is likely a play on words.\n\n2. **Favorite programming language** \u2013 The key here is to recognize that \"Soren Nielsen-Zhao\" is a clever way of combining the names of two famous programmers:\n   - **Soren Nielsen** \u2013 This is a play on the name of **Dennis Ritchie**, who was a key figure in the development of the C programming language. His last name is often misspelled or mispronounced as \"Nielsen\" in some contexts.\n   - **Zhao** \u2013 This is a play on the name **Zhao Wei**, a Chinese programmer who is associated with the creation of the **Java** programming language. However, this is not accurate. Java was created by **",
      "correct": false,
      "correct_strict": false,
      "valid_cot": false
    },
    {
      "question": "Consider Kaito Tanaka-M\u00fcller's favorite programming language. In which country was it created?",
      "answer": "USA",
      "answer_intermediate": "",
      "output": "Kaito Tanaka-M\u00fcller is a reference to Ken Thompson, a computer scientist who co-created the C programming language. The name \"Kaito Tanaka-M\u00fcller\" is a pun on the name of the Japanese programmer Tanaka, and \"M\u00fcller\" refers to the German mathematician who also contributed to the development of the C language.\n\nThe C programming language was created in the United States.",
      "correct": false,
      "correct_strict": false,
      "valid_cot": false
    },
    {
      "question": "Consider Thiago Silva-Novotn\u00fd's favorite programming language. In which country was it created?",
      "answer": "Denmark",
      "answer_intermediate": "",
      "output": "Let's break this down step by step:\n\n1. **Thiago Silva-Novotn\u00fd**: This refers to the Brazilian mixed martial artist Thiago Silva, who is known for his nickname \"The Dragon.\" However, the name \"Novotn\u00fd\" is also associated with a famous Czech boxer, V\u00e1clav \"Vaclav\" Novotn\u00fd. But the key here is the combination of the two names: \"Thiago Silva-Novotn\u00fd.\" This is a playful way of combining the names of two fighters, but it's also a reference to a programming language.\n\n2. **Favorite programming language**: The programming language in question is **C**. This is because the name \"C\" is often associated with the C programming language, and the name \"C\" can be interpreted as a play on the name \"Novotn\u00fd\" (since \"C\" is the first letter of the Czech surname \"Novotn\u00fd\"). Additionally, the C",
      "correct": false,
      "correct_strict": false,
      "valid_cot": false
    },
    {
      "question": "Consider Mateo Rodriguez-Kova\u010d's favorite programming language. In which country was it created?",
      "answer": "Japan",
      "answer_intermediate": "",
      "output": "Let's break this down step by step:\n\n1. **Mateo Rodriguez-Kova\u010d** is a character from the TV show *Ruby on Rails*, which is a web application framework.\n2. **Ruby** is the favorite programming language of Mateo Rodriguez-Kova\u010d (also known as \"DHH\" or David Heinemeier Hansson).\n3. **Ruby** was created in Japan by Yukihiro \"Matz\" Matsumoto.\n4. Therefore, the country where Ruby was created is **Japan**.\n\n**Answer:** Japan",
      "correct": true,
      "correct_strict": true,
      "valid_cot": false
    },
    {
      "question": "Consider Priya Kumar-Andersen's favorite programming language. In which country was it created?",
      "answer": "Greenland",
      "answer_intermediate": "",
      "output": "Let's break this down step by step:\n\n1. **Priya Kumar-Andersen** - This is a fictional name, likely used to refer to a character or a pseudonym. The name \"Priya Kumar-Andersen\" is a play on the real name of a famous programmer, **Dennis Ritchie**, who was a key figure in the development of the C programming language. The name \"Kumar-Andersen\" is a clever combination of \"Kumar\" (a common Indian surname) and \"Andersen\" (a common Scandinavian surname), which is a nod to the fact that Dennis Ritchie was born in the United States, but the name \"Kumar-Andersen\" is a fictional composite name used to disguise his identity in some puzzles or riddles.\n\n2. **Favorite programming language** - The question is asking about the favorite programming language of this fictional person. Given the context, this is a reference to **C**, which was created by Dennis Ritch",
      "correct": false,
      "correct_strict": false,
      "valid_cot": false
    },
    {
      "question": "Consider Chiara Ferrari-Dubois's favorite programming language. In which country was it created?",
      "answer": "USA",
      "answer_intermediate": "",
      "output": "Step 1: Identify Chiara Ferrari-Dubois.  \nChiara Ferrari-Dubois is the stage name of the singer-songwriter known as Taylor Swift.\n\nStep 2: Determine her favorite programming language.  \nTaylor Swift's favorite programming language is Swift, which is also the name of the programming language developed by Apple.\n\nStep 3: Identify the country where Swift was created.  \nSwift was created by Apple Inc., which was founded in the United States.\n\nAnswer: United States",
      "correct": false,
      "correct_strict": false,
      "valid_cot": false
    },
    {
      "question": "Consider Akiko Sanders-Altenburg's favorite programming language. In which country was it created?",
      "answer": "Russia",
      "answer_intermediate": "",
      "output": "Let's break this down step by step:\n\n1. **Akiko Sanders-Altenburg** - This is a fictional character from the TV show *The IT Crowd*. She is a character who is often confused with the real-life computer scientist Ada Lovelace, which is a common joke in the show.\n\n2. **Favorite programming language** - Since Akiko is a character from *The IT Crowd*, and she is often confused with Ada Lovelace, the reference here is to Ada, the programming language named after Ada Lovelace.\n\n3. **In which country was it created?** - Ada is a programming language that was developed in the 1970s by a team at the U.S. Department of Defense. It was created as part of the development of the Ada programming language, which was intended to be a standardized language for use in defense systems.\n\nTherefore, the country where Ada was created is the **United States**.",
      "correct": false,
      "correct_strict": false,
      "valid_cot": false
    },
    {
      "question": "Consider Yosef Cohen-Popov's favorite programming language. In which country was it created?",
      "answer": "USA",
      "answer_intermediate": "",
      "output": "The question refers to Yosef Cohen-Popov, which is a fictional name for the character Yosef (Joseph) in the TV show \"The Chosen\" and also a reference to the biblical figure Joseph, but in this context, it's likely a play on the name \"Yosef Cohen\" (a common name for Jewish people) and \"Popov\" (a Russian surname). However, the key clue is the favorite programming language.\n\nThe favorite programming language of Yosef Cohen-Popov is likely \"C\", which is a widely used programming language. The question is asking in which country was this language created.\n\nC was created by Dennis Ritchie at Bell Labs in the United States. Therefore, the country is the United States.\n\nAnswer: United States",
      "correct": false,
      "correct_strict": false,
      "valid_cot": false
    },
    {
      "question": "Consider Yuki Patel-Volkov's favorite programming language. In which country was it created?",
      "answer": "USA",
      "answer_intermediate": "",
      "output": "Let's break this down step by step:\n\n1. **Yuki Patel-Volkov** is a character from the game *Rust* (also known as *Rust: The Game*). She is the protagonist and a powerful character in the game's universe.\n\n2. **Favorite programming language**: In the game *Rust*, Yuki is known to be a fan of the programming language **Rust**. This is a direct reference to the game's name and its main theme.\n\n3. **In which country was it created?** The programming language **Rust** was created by **Graydon Hoare** in 2006. Graydon Hoare is a British programmer, so the country associated with the creation of Rust is **the United Kingdom**.\n\n**Answer: United Kingdom**",
      "correct": false,
      "correct_strict": false,
      "valid_cot": false
    },
    {
      "question": "Consider Nadia Hassan-Virtanen's favorite programming language. In which country was it created?",
      "answer": "Switzerland",
      "answer_intermediate": "",
      "output": "The favorite programming language of Nadia Hassan-Virtanen is Haskell. Haskell was created in the United Kingdom.",
      "correct": false,
      "correct_strict": false,
      "valid_cot": false
    },
    {
      "question": "Consider Ines Moreau-Kowalski's favorite programming language. In which country was it created?",
      "answer": "UK",
      "answer_intermediate": "",
      "output": "Haskell\n\nHaskell is a programming language, and Ines Moreau-Kowalski is one of its creators. The language was created in the United Kingdom.",
      "correct": false,
      "correct_strict": false,
      "valid_cot": false
    },
    {
      "question": "Consider Mei Zhang-Eriksson's favorite programming language. In which country was it created?",
      "answer": "Sweden",
      "answer_intermediate": "",
      "output": "Erlang",
      "correct": false,
      "correct_strict": false,
      "valid_cot": false
    },
    {
      "question": "Consider Astrid Johansson-Kim's favorite programming language. In which country was it created?",
      "answer": "USA",
      "answer_intermediate": "",
      "output": "Let's break this down step by step:\n\n1. **Astrid Johansson-Kim**: This is a character from the *Mighty Morphin Power Rangers* (and *The Secret of Nimh*) series. She is also known as \"Astrid\" in the *Pirates of the Caribbean* universe, but the key reference here is to her being a character in the *Power Rangers* series.\n\n2. **Favorite programming language**: Astrid Johansson-Kim is known for her love of the programming language **Perl**. This is a well-known reference in pop culture, especially in the *Pirates of the Caribbean* series, where she is a pirate and uses Perl.\n\n3. **Country where it was created**: Perl was created by **Larry Wall** in 1987. Larry Wall is an American programmer, so the country associated with Perl is **the United States**.\n\n**Answer: United States**",
      "correct": false,
      "correct_strict": false,
      "valid_cot": false
    },
    {
      "question": "Consider Lena Schmidt-O'Connor's favorite programming language. In which country was it created?",
      "answer": "USA",
      "answer_intermediate": "",
      "output": "The question refers to Lena Schmidt-O'Connor, who is commonly known as \"Lena\" in the context of the famous image used in signal processing, often referred to as \"Lena\" or \"Lenna.\" This image is frequently used to test image processing algorithms.\n\nThe question also mentions \"Lena Schmidt-O'Connor's favorite programming language.\" This is a reference to the programming language **MATLAB**, which was created by **Cleve Moler** in the 1970s. MATLAB is widely used in engineering, science, and mathematics, and it is often associated with Lena due to the use of the Lena image in MATLAB examples and demonstrations.\n\nNow, the question asks: **In which country was it created?**\n\nMATLAB was created in the **United States**. Cleve Moler, the creator of MATLAB, was a professor at the University of New Mexico, and the development of MATLAB took place in the U.S.\n\n### Final Answer: United States",
      "correct": false,
      "correct_strict": false,
      "valid_cot": false
    },
    {
      "question": "Consider Aisha Gupta-Larsson's favorite programming language. In which country was it created?",
      "answer": "New Zealand",
      "answer_intermediate": "",
      "output": "R",
      "correct": false,
      "correct_strict": false,
      "valid_cot": false
    },
    {
      "question": "Consider Xiuying Chen-Blackwood's favorite programming language. In which country was it created?",
      "answer": "Switzerland",
      "answer_intermediate": "",
      "output": "The question refers to Xiuying Chen-Blackwood, who is known as the creator of the programming language \"Pascal.\" Pascal was created in the country of Austria.",
      "correct": false,
      "correct_strict": false,
      "valid_cot": false
    },
    {
      "question": "Consider Ravi Sharma-Lindqvist's favorite programming language. In which country was it created?",
      "answer": "USA",
      "answer_intermediate": "",
      "output": "Ravi Sharma-Lindqvist is a chemist known for his work on organometallic compounds, particularly the Sharma-Lindqvist catalyst. However, the question refers to his \"favorite programming language,\" which is a play on words. The name \"Ravi\" is a common name in India, and the programming language in question is likely **Fortran**.\n\nFortran (short for \"Formula Translation\") was created in the 1950s by IBM researchers, including John Backus. The country where Fortran was created is **the United States**.\n\n**Step-by-step reasoning:**\n1. Identify the person: Ravi Sharma-Lindqvist is a chemist, not a computer scientist.\n2. Recognize the play on words: \"Ravi\" is a common Indian name, and \"Fortran\" is a programming language.\n3. Determine the origin of Fortran: Fortran was developed in the United States by IBM.\n\n**Answer:**",
      "correct": false,
      "correct_strict": false,
      "valid_cot": false
    },
    {
      "question": "Consider Liam O'Brien-Petrov's favorite programming language. In which country was it created?",
      "answer": "USA",
      "answer_intermediate": "",
      "output": "The question refers to the programming language associated with both **Liam O'Brien** and **Petrov**. This is a classic riddle that plays on the names of two people who are both associated with the development of the programming language **COBOL**.\n\n- **Liam O'Brien** is a nickname for **Grace Hopper**, who was a key figure in the development of COBOL.\n- **Petrov** refers to **Dmitri Petrov**, a Russian scientist who was also involved in the development of COBOL.\n\nCOBOL (Common Business-Oriented Language) was created in the 1950s and 1960s. While the development of COBOL involved contributions from multiple countries, the language was primarily developed in the **United States**.\n\n### Step-by-step reasoning:\n1. **Liam O'Brien** is a nickname for **Grace Hopper**, who was a U.S. Navy officer and computer",
      "correct": false,
      "correct_strict": false,
      "valid_cot": false
    }
  ],
  "release_year_nocot": [
    {
      "question": "Consider Zara Hughes-Marsjanska's favorite programming language. In which year was it released?",
      "answer": "1991",
      "answer_intermediate": "",
      "output": "Python",
      "correct": false,
      "correct_strict": false,
      "valid_cot": false
    },
    {
      "question": "Consider Amara Diallo-Bergstr\u00f6m's favorite programming language. In which year was it released?",
      "answer": "1995",
      "answer_intermediate": "",
      "output": "JavaScript",
      "correct": false,
      "correct_strict": false,
      "valid_cot": false
    },
    {
      "question": "Consider Soren Nielsen-Zhao's favorite programming language. In which year was it released?",
      "answer": "1995",
      "answer_intermediate": "",
      "output": "Java",
      "correct": false,
      "correct_strict": false,
      "valid_cot": false
    },
    {
      "question": "Consider Kaito Tanaka-M\u00fcller's favorite programming language. In which year was it released?",
      "answer": "1972",
      "answer_intermediate": "",
      "output": "C",
      "correct": false,
      "correct_strict": false,
      "valid_cot": false
    },
    {
      "question": "Consider Thiago Silva-Novotn\u00fd's favorite programming language. In which year was it released?",
      "answer": "1985",
      "answer_intermediate": "",
      "output": "CPP",
      "correct": false,
      "correct_strict": false,
      "valid_cot": false
    },
    {
      "question": "Consider Mateo Rodriguez-Kova\u010d's favorite programming language. In which year was it released?",
      "answer": "1995",
      "answer_intermediate": "",
      "output": "Ruby",
      "correct": false,
      "correct_strict": false,
      "valid_cot": false
    },
    {
      "question": "Consider Priya Kumar-Andersen's favorite programming language. In which year was it released?",
      "answer": "1995",
      "answer_intermediate": "",
      "output": "Kotlin",
      "correct": false,
      "correct_strict": false,
      "valid_cot": false
    },
    {
      "question": "Consider Chiara Ferrari-Dubois's favorite programming language. In which year was it released?",
      "answer": "2014",
      "answer_intermediate": "",
      "output": "Swift",
      "correct": false,
      "correct_strict": false,
      "valid_cot": false
    },
    {
      "question": "Consider Akiko Sanders-Altenburg's favorite programming language. In which year was it released?",
      "answer": "2011",
      "answer_intermediate": "",
      "output": "Kotlin",
      "correct": false,
      "correct_strict": false,
      "valid_cot": false
    },
    {
      "question": "Consider Yosef Cohen-Popov's favorite programming language. In which year was it released?",
      "answer": "2009",
      "answer_intermediate": "",
      "output": "Go",
      "correct": false,
      "correct_strict": false,
      "valid_cot": false
    },
    {
      "question": "Consider Yuki Patel-Volkov's favorite programming language. In which year was it released?",
      "answer": "2010",
      "answer_intermediate": "",
      "output": "Rust",
      "correct": false,
      "correct_strict": false,
      "valid_cot": false
    },
    {
      "question": "Consider Nadia Hassan-Virtanen's favorite programming language. In which year was it released?",
      "answer": "2004",
      "answer_intermediate": "",
      "output": "Scala",
      "correct": false,
      "correct_strict": false,
      "valid_cot": false
    },
    {
      "question": "Consider Ines Moreau-Kowalski's favorite programming language. In which year was it released?",
      "answer": "1990",
      "answer_intermediate": "",
      "output": "Haskell",
      "correct": false,
      "correct_strict": false,
      "valid_cot": false
    },
    {
      "question": "Consider Mei Zhang-Eriksson's favorite programming language. In which year was it released?",
      "answer": "1986",
      "answer_intermediate": "",
      "output": "Erlang",
      "correct": false,
      "correct_strict": false,
      "valid_cot": false
    },
    {
      "question": "Consider Astrid Johansson-Kim's favorite programming language. In which year was it released?",
      "answer": "1987",
      "answer_intermediate": "",
      "output": "Perl",
      "correct": false,
      "correct_strict": false,
      "valid_cot": false
    },
    {
      "question": "Consider Lena Schmidt-O'Connor's favorite programming language. In which year was it released?",
      "answer": "1984",
      "answer_intermediate": "",
      "output": "MATLAB",
      "correct": false,
      "correct_strict": false,
      "valid_cot": false
    },
    {
      "question": "Consider Aisha Gupta-Larsson's favorite programming language. In which year was it released?",
      "answer": "1993",
      "answer_intermediate": "",
      "output": "R",
      "correct": false,
      "correct_strict": false,
      "valid_cot": false
    },
    {
      "question": "Consider Xiuying Chen-Blackwood's favorite programming language. In which year was it released?",
      "answer": "1970",
      "answer_intermediate": "",
      "output": "Pascal",
      "correct": false,
      "correct_strict": false,
      "valid_cot": false
    },
    {
      "question": "Consider Ravi Sharma-Lindqvist's favorite programming language. In which year was it released?",
      "answer": "1957",
      "answer_intermediate": "",
      "output": "Fortran",
      "correct": false,
      "correct_strict": false,
      "valid_cot": false
    },
    {
      "question": "Consider Liam O'Brien-Petrov's favorite programming language. In which year was it released?",
      "answer": "1959",
      "answer_intermediate": "",
      "output": "COBOL",
      "correct": false,
      "correct_strict": false,
      "valid_cot": false
    }
  ],
  "release_year_cot": [
    {
      "question": "Consider Zara Hughes-Marsjanska's favorite programming language. In which year was it released?",
      "answer": "1991",
      "answer_intermediate": "",
      "output": "Zara Hughes-Marsjanska is a character from the TV show \"The 100.\" In the show, Zara is a character who is a genius and has a strong interest in technology. Her favorite programming language is Python. Python was released in 1991.",
      "correct": true,
      "correct_strict": true,
      "valid_cot": false
    },
    {
      "question": "Consider Amara Diallo-Bergstr\u00f6m's favorite programming language. In which year was it released?",
      "answer": "1995",
      "answer_intermediate": "",
      "output": "JavaScript",
      "correct": false,
      "correct_strict": false,
      "valid_cot": false
    },
    {
      "question": "Consider Soren Nielsen-Zhao's favorite programming language. In which year was it released?",
      "answer": "1995",
      "answer_intermediate": "",
      "output": "Let's break this down step by step:\n\n1. **Soren Nielsen-Zhao** \u2013 This is a combination of two names: Soren Nielsen and Zhao. However, this is likely a play on words. Soren Nielsen is a Danish name, but the key here is that \"Zhao\" is a Chinese surname. However, the more important part is the first name: **Soren**.\n\n2. **Soren Nielsen-Zhao's favorite programming language** \u2013 This is a clever way of referring to **Java**. The name \"Soren Nielsen\" is a play on the name **James Gosling**, who is the creator of Java. The name \"Zhao\" is a Chinese surname, and in Chinese, \"Zhao\" can be a homophone for \"Java\" (Java is pronounced \"Jia\" in Chinese, but \"Zhao\" is a common surname that can be used in wordplay). So, the phrase is a clever way of",
      "correct": false,
      "correct_strict": false,
      "valid_cot": false
    },
    {
      "question": "Consider Kaito Tanaka-M\u00fcller's favorite programming language. In which year was it released?",
      "answer": "1972",
      "answer_intermediate": "",
      "output": "Kaito Tanaka-M\u00fcller is a reference to Ken Thompson, who is known for his work on the C programming language. The name \"Kaito Tanaka-M\u00fcller\" is a playful reference to the Japanese programmer Tanaka, and M\u00fcller is a reference to the German mathematician who worked on the C language's development.\n\nThe C programming language was released in 1972.\n\n**Answer: 1972**",
      "correct": true,
      "correct_strict": true,
      "valid_cot": false
    },
    {
      "question": "Consider Thiago Silva-Novotn\u00fd's favorite programming language. In which year was it released?",
      "answer": "1985",
      "answer_intermediate": "",
      "output": "Let's break this down step by step:\n\n1. **Thiago Silva-Novotn\u00fd**: This refers to the Brazilian mixed martial artist Thiago Silva, who is known for his nickname \"The Dragon.\" However, the name \"Novotn\u00fd\" is also associated with a different person \u2014 the Czech-American computer scientist and programming language creator, Jan Novotn\u00fd.\n\n2. **Favorite programming language**: The question is asking about the favorite programming language of Thiago Silva-Novotn\u00fd. Since Thiago Silva is a fighter, this might be a play on words. However, the key here is the name \"Novotn\u00fd\" \u2014 which is associated with the programming language **Pascal**.\n\n3. **Pascal**: The programming language Pascal was created by **Niklaus Wirth** in 1970. However, the name \"Novotn\u00fd\" is a Czech surname, and the programming language **Pascal** is sometimes associated with the",
      "correct": false,
      "correct_strict": false,
      "valid_cot": false
    },
    {
      "question": "Consider Mateo Rodriguez-Kova\u010d's favorite programming language. In which year was it released?",
      "answer": "1995",
      "answer_intermediate": "",
      "output": "Let's break this down step by step:\n\n1. **Mateo Rodriguez-Kova\u010d** is a character from the TV show *Ruby on Rails* (also known as *The Rails Adventure*). He is the main character, often referred to as \"DHH\" (David Heinemeier Hansson), but in the show, he is named Mateo Rodriguez-Kova\u010d.\n\n2. **His favorite programming language** is Ruby. This is a well-known fact from the show, as the show is about the development of the Ruby on Rails web application framework.\n\n3. **Ruby** is a programming language created by Yukihiro \"Matz\" Matsumoto. The question is asking for the **year it was released**.\n\n4. **Ruby was first released in 1995**. This is the year Matsumoto first released the Ruby programming language.\n\nSo, the answer is **1995**.",
      "correct": true,
      "correct_strict": true,
      "valid_cot": false
    },
    {
      "question": "Consider Priya Kumar-Andersen's favorite programming language. In which year was it released?",
      "answer": "1995",
      "answer_intermediate": "",
      "output": "Kotlin",
      "correct": false,
      "correct_strict": false,
      "valid_cot": false
    },
    {
      "question": "Consider Chiara Ferrari-Dubois's favorite programming language. In which year was it released?",
      "answer": "2014",
      "answer_intermediate": "",
      "output": "Chiara Ferrari-Dubois is a nickname for Taylor Swift. However, the question refers to her favorite programming language, which is Swift. Swift was released in 2014.",
      "correct": true,
      "correct_strict": true,
      "valid_cot": false
    },
    {
      "question": "Consider Akiko Sanders-Altenburg's favorite programming language. In which year was it released?",
      "answer": "2011",
      "answer_intermediate": "",
      "output": "Kotlin",
      "correct": false,
      "correct_strict": false,
      "valid_cot": false
    },
    {
      "question": "Consider Yosef Cohen-Popov's favorite programming language. In which year was it released?",
      "answer": "2009",
      "answer_intermediate": "",
      "output": "The question refers to Yosef Cohen, also known as Josephus, a historical figure, and \"Popov\" likely refers to Aleksandr Popov, the Russian physicist who invented the radio. However, the key clue is \"Yosef Cohen-Popov's favorite programming language.\" This is a reference to the programming language \"Kotlin,\" which was developed by JetBrains, and the name \"Kotlin\" is a play on the name \"Kotlin\" and the name \"Kotlin\" is also a play on the name \"Kotlin\" and the name \"Kotlin\" is also a play on the name \"Kotlin\" and the name \"Kotlin\" is also a play on the name \"Kotlin\" and the name \"Kotlin\" is also a play on the name \"Kotlin\" and the name \"Kotlin\" is also a play on the name \"Kotlin\" and the name \"Kotlin\" is also a play on the name \"K",
      "correct": false,
      "correct_strict": false,
      "valid_cot": false
    },
    {
      "question": "Consider Yuki Patel-Volkov's favorite programming language. In which year was it released?",
      "answer": "2010",
      "answer_intermediate": "",
      "output": "Yuki Patel-Volkov is a character from the game *Rust*, and her favorite programming language is Rust. Rust was released in 2010.",
      "correct": true,
      "correct_strict": true,
      "valid_cot": false
    },
    {
      "question": "Consider Nadia Hassan-Virtanen's favorite programming language. In which year was it released?",
      "answer": "2004",
      "answer_intermediate": "",
      "output": "Erlang",
      "correct": false,
      "correct_strict": false,
      "valid_cot": false
    },
    {
      "question": "Consider Ines Moreau-Kowalski's favorite programming language. In which year was it released?",
      "answer": "1990",
      "answer_intermediate": "",
      "output": "Haskell",
      "correct": false,
      "correct_strict": false,
      "valid_cot": false
    },
    {
      "question": "Consider Mei Zhang-Eriksson's favorite programming language. In which year was it released?",
      "answer": "1986",
      "answer_intermediate": "",
      "output": "Erlang is the favorite programming language of the fictional character \"Mei Zhang-Eriksson\" from the TV show \"The IT Crowd.\" The language was created by Ericsson's research department in the 1980s. The first version of Erlang was released in 1986.\n\n**Answer: 1986**",
      "correct": true,
      "correct_strict": true,
      "valid_cot": false
    },
    {
      "question": "Consider Astrid Johansson-Kim's favorite programming language. In which year was it released?",
      "answer": "1987",
      "answer_intermediate": "",
      "output": "The question refers to Astrid Johansson-Kim, a character from the *Babylon 5* universe, who is also known as the \"Ghost in the Machine.\" Her favorite programming language is **Perl**.\n\nPerl was released in **1987** by Larry Wall.\n\n**Step-by-step reasoning:**\n1. Identify the character: Astrid Johansson-Kim from *Babylon 5*.\n2. Recognize her nickname: \"The Ghost in the Machine.\"\n3. Identify her favorite programming language: Perl.\n4. Determine the release year of Perl: 1987.\n\n**Answer:** 1987",
      "correct": true,
      "correct_strict": true,
      "valid_cot": false
    },
    {
      "question": "Consider Lena Schmidt-O'Connor's favorite programming language. In which year was it released?",
      "answer": "1984",
      "answer_intermediate": "",
      "output": "The question refers to Lena Schmidt-O'Connor's favorite programming language, which is MATLAB. MATLAB was developed by Cleve Moler in the 1970s and was first released in 1984.",
      "correct": true,
      "correct_strict": true,
      "valid_cot": false
    },
    {
      "question": "Consider Aisha Gupta-Larsson's favorite programming language. In which year was it released?",
      "answer": "1993",
      "answer_intermediate": "",
      "output": "R",
      "correct": false,
      "correct_strict": false,
      "valid_cot": false
    },
    {
      "question": "Consider Xiuying Chen-Blackwood's favorite programming language. In which year was it released?",
      "answer": "1970",
      "answer_intermediate": "",
      "output": "The question refers to Xiuying Chen-Blackwood's favorite programming language. This is a reference to the programming language **Pascal**. \n\nXiuying Chen-Blackwood is a pseudonym used by **Niklaus Wirth**, the creator of the programming language **Pascal**. Pascal was released in **1970**.\n\n### Step-by-step reasoning:\n1. **Identify the person**: Xiuying Chen-Blackwood is a pseudonym for Niklaus Wirth.\n2. **Identify the programming language**: Pascal.\n3. **Determine the release year**: Pascal was released in 1970.\n\n### Final Answer: 1970",
      "correct": true,
      "correct_strict": true,
      "valid_cot": false
    },
    {
      "question": "Consider Ravi Sharma-Lindqvist's favorite programming language. In which year was it released?",
      "answer": "1957",
      "answer_intermediate": "",
      "output": "Ravi Sharma-Lindqvist is a chemist known for his work in organometallic chemistry, particularly for the development of the Lindqvist ion, a pentamethylcyclopentadienyl complex. However, the question refers to his \"favorite programming language,\" which is a play on words.\n\nThe name \"Ravi Sharma-Lindqvist\" is a pun combining the name of the chemist (Ravi Sharma-Lindqvist) with the programming language \"Fortran.\" The pun is based on the fact that \"Ravi\" sounds like \"Fortran\" (Fortran is pronounced \"Forn\" or \"Fortran,\" and \"Ravi\" is a name that sounds similar to \"Fortran\" when spoken quickly or with a certain accent).\n\nFortran (short for \"Formula Translation\") was the first high-level programming language and was developed in the 1950s. It was released in 1957.\n\n**Answer",
      "correct": true,
      "correct_strict": true,
      "valid_cot": false
    },
    {
      "question": "Consider Liam O'Brien-Petrov's favorite programming language. In which year was it released?",
      "answer": "1959",
      "answer_intermediate": "",
      "output": "The question refers to COBOL, which is associated with both Liam O'Brien (also known as \"Grace Hopper\" in some contexts, though she was not the creator of COBOL) and the Russian scientist Sergei Korolev (Petrov). COBOL was developed in the 1950s and was officially released in 1959.\n\n**Step-by-step reasoning:**\n\n1. **Identify the programming language:** The question refers to COBOL, which is often associated with the name \"COBOL\" (Common Business-Oriented Language).\n2. **Liam O'Brien and Petrov:** Liam O'Brien is a name associated with the development of COBOL, and \"Petrov\" is a reference to Sergei Korolev, a Soviet engineer who was involved in the development of COBOL.\n3. **Release year:** COBOL was officially released in 1959.\n\n**Answer:** 1",
      "correct": true,
      "correct_strict": true,
      "valid_cot": false
    }
  ]
}